instancelib/__init__.py
instancelib/py.typed
instancelib/analysis/__init__.py
instancelib/analysis/base.py
instancelib/environment/__init__.py
instancelib/environment/base.py
instancelib/environment/hdf5.py
instancelib/environment/huggingface.py
instancelib/environment/memory.py
instancelib/environment/text.py
instancelib/exceptions/__init__.py
instancelib/exceptions/base.py
instancelib/export/__init__.py
instancelib/export/pandas.py
instancelib/feature_extraction/__init__.py
instancelib/feature_extraction/base.py
instancelib/feature_extraction/doc2vec.py
instancelib/feature_extraction/textinstance.py
instancelib/feature_extraction/textsklearn.py
instancelib/functions/__init__.py
instancelib/functions/vectorize.py
instancelib/ingest/__init__.py
instancelib/ingest/qrel.py
instancelib/ingest/spreadsheet.py
instancelib/instances/__init__.py
instancelib/instances/base.py
instancelib/instances/children.py
instancelib/instances/combination.py
instancelib/instances/dataset.py
instancelib/instances/external.py
instancelib/instances/extractors.py
instancelib/instances/hdf5.py
instancelib/instances/hdf5pandas.py
instancelib/instances/hdf5vector.py
instancelib/instances/huggingface.py
instancelib/instances/memory.py
instancelib/instances/memoryvectorstorage.py
instancelib/instances/tablebacked.py
instancelib/instances/text.py
instancelib/instances/vectorstorage.py
instancelib/labels/__init__.py
instancelib/labels/base.py
instancelib/labels/encoder.py
instancelib/labels/memory.py
instancelib/machinelearning/__init__.py
instancelib/machinelearning/autovectorizer.py
instancelib/machinelearning/base.py
instancelib/machinelearning/featurematrix.py
instancelib/machinelearning/huggingface.py
instancelib/machinelearning/skdata.py
instancelib/machinelearning/sklearn.py
instancelib/machinelearning/skvectors.py
instancelib/machinelearning/wrapper.py
instancelib/pertubations/__init__.py
instancelib/pertubations/base.py
instancelib/typehints/__init__.py
instancelib/typehints/typevars.py
instancelib-0.5.2.dist-info/LICENSE
instancelib-0.5.2.dist-info/METADATA
instancelib-0.5.2.dist-info/WHEEL
instancelib-0.5.2.dist-info/top_level.txt
instancelib-0.5.2.dist-info/RECORD
