Metadata-Version: 2.2
Name: instancelib
Version: 0.5.2
Summary: A generic interface for datasets and Machine Learning models
Author: Michiel Bron
Author-email: m.p.bron@uu.nl
License: GNU LGPL v3
Classifier: License :: OSI Approved :: GNU Lesser General Public License v3 or later (LGPLv3+)
Classifier: Programming Language :: Python
Classifier: Topic :: Scientific/Engineering :: Artificial Intelligence
Requires-Python: >=3.8
License-File: LICENSE
Requires-Dist: numpy
Requires-Dist: pandas
Requires-Dist: h5py
Requires-Dist: scikit-learn
Requires-Dist: openpyxl
Requires-Dist: xlrd
Requires-Dist: tqdm
Requires-Dist: more-itertools
Requires-Dist: typing_extensions
Provides-Extra: doc2vec
Requires-Dist: gensim; extra == "doc2vec"
Provides-Extra: hdf5
Requires-Dist: tables; extra == "hdf5"
Dynamic: author
Dynamic: author-email
Dynamic: classifier
Dynamic: description
Dynamic: description-content-type
Dynamic: license
Dynamic: provides-extra
Dynamic: requires-dist
Dynamic: requires-python
Dynamic: summary
